snowflow/__init__.py
snowflow/commands.py
snowflow/handler.py
snowflow/runner.py
snowflow/scripts.py
snowflow/sf_task_template.sql
snowflow/sql_procedure_template.sql
snowflow/user_task_template.sql
snowflow-0.0.15.dist-info/LICENSE
snowflow-0.0.15.dist-info/METADATA
snowflow-0.0.15.dist-info/WHEEL
snowflow-0.0.15.dist-info/entry_points.txt
snowflow-0.0.15.dist-info/top_level.txt
snowflow-0.0.15.dist-info/RECORD
