Metadata-Version: 2.1
Name: snowflow
Version: 0.0.15
Summary: SnowFlow - A Snowflake Deployment Tool
Author: Thomas Garcia, Aryan Singh
Author-email: tgarcia@svam.com, aryan.singh@svam.com
License: BSD-3-Clause
Classifier: Programming Language :: Python :: 3
Classifier: License :: OSI Approved :: BSD License
Classifier: Operating System :: OS Independent
Requires-Python: >=3.6
License-File: LICENSE
Requires-Dist: snowflake-connector-python
Requires-Dist: snowflake-snowpark-python
Requires-Dist: snowflake-connector-python[secure-local-storage]
Requires-Dist: networkx
Requires-Dist: pyyaml
Requires-Dist: toml
